{"/*":["X-Frame-Options: DENY","X-XSS-Protection: 1; mode=block","X-Content-Type-Options: nosniff","Referrer-Policy: same-origin"],"/styles.accc8a0ce3adf6b87a68.css":["Cache-Control: public, max-age=31536000, immutable"],"/commons-5e092f0f9cb5bcd207bc.js":["Cache-Control: public, max-age=31536000, immutable"],"/component---src-pages-404-js-41b4239d81b93ee661bd.js":["Cache-Control: public, max-age=31536000, immutable"],"/cb1608f2-52a49d76d2490af95d87.js":["Cache-Control: public, max-age=31536000, immutable"],"/a9a7754c-64a7f97dfad08f666098.js":["Cache-Control: public, max-age=31536000, immutable"],"/b97f41514cc73042bacccd750b918c6c32686fb3-54888468d8e58edf626f.js":["Cache-Control: public, max-age=31536000, immutable"],"/component---src-pages-dormitory-tsx-c266a642d04ba258c4d4.js":["Cache-Control: public, max-age=31536000, immutable"],"/component---src-pages-how-to-use-tsx-7e983d42a70d3b6d0605.js":["Cache-Control: public, max-age=31536000, immutable"],"/component---src-pages-index-tsx-921c05945e65ea84fe07.js":["Cache-Control: public, max-age=31536000, immutable"],"/component---src-pages-term-tsx-188595ac4e02e1a32dd8.js":["Cache-Control: public, max-age=31536000, immutable"],"/component---src-pages-update-history-tsx-2a347f46bc1352c2e3dc.js":["Cache-Control: public, max-age=31536000, immutable"],"/webpack-runtime-fe35cc287bbaac180823.js":["Cache-Control: public, max-age=31536000, immutable"],"/framework-e2f64ce74f6cee9d1a0b.js":["Cache-Control: public, max-age=31536000, immutable"],"/app-46447957b512445d4465.js":["Cache-Control: public, max-age=31536000, immutable"],"/static/*":["Cache-Control: public, max-age=31536000, immutable"],"/sw.js":["Cache-Control: public, max-age=0, must-revalidate"],"/404/":["Link: </webpack-runtime-fe35cc287bbaac180823.js>; rel=preload; as=script; nopush","Link: </framework-e2f64ce74f6cee9d1a0b.js>; rel=preload; as=script; nopush","Link: </app-46447957b512445d4465.js>; rel=preload; as=script; nopush","Link: </commons-5e092f0f9cb5bcd207bc.js>; rel=preload; as=script; nopush","Link: </component---src-pages-404-js-41b4239d81b93ee661bd.js>; rel=preload; as=script; nopush","Link: </page-data/app-data.json>; rel=preload; as=fetch; crossorigin; nopush","Link: </page-data/404/page-data.json>; rel=preload; as=fetch; crossorigin; nopush"],"/404.html":["Link: </webpack-runtime-fe35cc287bbaac180823.js>; rel=preload; as=script; nopush","Link: </framework-e2f64ce74f6cee9d1a0b.js>; rel=preload; as=script; nopush","Link: </app-46447957b512445d4465.js>; rel=preload; as=script; nopush","Link: </commons-5e092f0f9cb5bcd207bc.js>; rel=preload; as=script; nopush","Link: </component---src-pages-404-js-41b4239d81b93ee661bd.js>; rel=preload; as=script; nopush","Link: </page-data/app-data.json>; rel=preload; as=fetch; crossorigin; nopush","Link: </page-data/404.html/page-data.json>; rel=preload; as=fetch; crossorigin; nopush"],"/dormitory/":["Link: </webpack-runtime-fe35cc287bbaac180823.js>; rel=preload; as=script; nopush","Link: </framework-e2f64ce74f6cee9d1a0b.js>; rel=preload; as=script; nopush","Link: </app-46447957b512445d4465.js>; rel=preload; as=script; nopush","Link: </cb1608f2-52a49d76d2490af95d87.js>; rel=preload; as=script; nopush","Link: </a9a7754c-64a7f97dfad08f666098.js>; rel=preload; as=script; nopush","Link: </commons-5e092f0f9cb5bcd207bc.js>; rel=preload; as=script; nopush","Link: </b97f41514cc73042bacccd750b918c6c32686fb3-54888468d8e58edf626f.js>; rel=preload; as=script; nopush","Link: </component---src-pages-dormitory-tsx-c266a642d04ba258c4d4.js>; rel=preload; as=script; nopush","Link: </page-data/app-data.json>; rel=preload; as=fetch; crossorigin; nopush","Link: </page-data/dormitory/page-data.json>; rel=preload; as=fetch; crossorigin; nopush"],"/how_to_use/":["Link: </webpack-runtime-fe35cc287bbaac180823.js>; rel=preload; as=script; nopush","Link: </framework-e2f64ce74f6cee9d1a0b.js>; rel=preload; as=script; nopush","Link: </app-46447957b512445d4465.js>; rel=preload; as=script; nopush","Link: </cb1608f2-52a49d76d2490af95d87.js>; rel=preload; as=script; nopush","Link: </a9a7754c-64a7f97dfad08f666098.js>; rel=preload; as=script; nopush","Link: </commons-5e092f0f9cb5bcd207bc.js>; rel=preload; as=script; nopush","Link: </b97f41514cc73042bacccd750b918c6c32686fb3-54888468d8e58edf626f.js>; rel=preload; as=script; nopush","Link: </component---src-pages-how-to-use-tsx-7e983d42a70d3b6d0605.js>; rel=preload; as=script; nopush","Link: </page-data/app-data.json>; rel=preload; as=fetch; crossorigin; nopush","Link: </page-data/how_to_use/page-data.json>; rel=preload; as=fetch; crossorigin; nopush"],"/":["Link: </webpack-runtime-fe35cc287bbaac180823.js>; rel=preload; as=script; nopush","Link: </framework-e2f64ce74f6cee9d1a0b.js>; rel=preload; as=script; nopush","Link: </app-46447957b512445d4465.js>; rel=preload; as=script; nopush","Link: </cb1608f2-52a49d76d2490af95d87.js>; rel=preload; as=script; nopush","Link: </a9a7754c-64a7f97dfad08f666098.js>; rel=preload; as=script; nopush","Link: </commons-5e092f0f9cb5bcd207bc.js>; rel=preload; as=script; nopush","Link: </b97f41514cc73042bacccd750b918c6c32686fb3-54888468d8e58edf626f.js>; rel=preload; as=script; nopush","Link: </component---src-pages-index-tsx-921c05945e65ea84fe07.js>; rel=preload; as=script; nopush","Link: </page-data/app-data.json>; rel=preload; as=fetch; crossorigin; nopush","Link: </page-data/index/page-data.json>; rel=preload; as=fetch; crossorigin; nopush"],"/term/":["Link: </webpack-runtime-fe35cc287bbaac180823.js>; rel=preload; as=script; nopush","Link: </framework-e2f64ce74f6cee9d1a0b.js>; rel=preload; as=script; nopush","Link: </app-46447957b512445d4465.js>; rel=preload; as=script; nopush","Link: </cb1608f2-52a49d76d2490af95d87.js>; rel=preload; as=script; nopush","Link: </a9a7754c-64a7f97dfad08f666098.js>; rel=preload; as=script; nopush","Link: </commons-5e092f0f9cb5bcd207bc.js>; rel=preload; as=script; nopush","Link: </b97f41514cc73042bacccd750b918c6c32686fb3-54888468d8e58edf626f.js>; rel=preload; as=script; nopush","Link: </component---src-pages-term-tsx-188595ac4e02e1a32dd8.js>; rel=preload; as=script; nopush","Link: </page-data/app-data.json>; rel=preload; as=fetch; crossorigin; nopush","Link: </page-data/term/page-data.json>; rel=preload; as=fetch; crossorigin; nopush"],"/update_history/":["Link: </webpack-runtime-fe35cc287bbaac180823.js>; rel=preload; as=script; nopush","Link: </framework-e2f64ce74f6cee9d1a0b.js>; rel=preload; as=script; nopush","Link: </app-46447957b512445d4465.js>; rel=preload; as=script; nopush","Link: </cb1608f2-52a49d76d2490af95d87.js>; rel=preload; as=script; nopush","Link: </a9a7754c-64a7f97dfad08f666098.js>; rel=preload; as=script; nopush","Link: </commons-5e092f0f9cb5bcd207bc.js>; rel=preload; as=script; nopush","Link: </b97f41514cc73042bacccd750b918c6c32686fb3-54888468d8e58edf626f.js>; rel=preload; as=script; nopush","Link: </component---src-pages-update-history-tsx-2a347f46bc1352c2e3dc.js>; rel=preload; as=script; nopush","Link: </page-data/app-data.json>; rel=preload; as=fetch; crossorigin; nopush","Link: </page-data/update_history/page-data.json>; rel=preload; as=fetch; crossorigin; nopush"]}